{
    "__1996_Fast_string_searching": {
        "container_type": "Publication",
        "source": "PUBLICATION_SEARCH_SNIPPET",
        "bib": {
            "title": "Fast string searching in secondary storage: Theoretical developments and experimental results",
            "author": [
                "P Ferragina",
                "R Grossi"
            ],
            "pub_year": "1996",
            "venue": "Proceedings of the seventh annual ACM-SIAM \u2026",
            "abstract": "In a previous work [S], we proposed a text indexing data structure for secondary storage, which we called SB-tree, that combines the best of B-trees and suffix arrays, overcoming the"
        },
        "filled": false,
        "gsrank": 1,
        "pub_url": "https://dl.acm.org/doi/pdf/10.5555/313852.314086",
        "author_id": [
            "3EILU3MAAAAJ",
            "yZTneswAAAAJ"
        ],
        "url_scholarbib": "/scholar?hl=en&q=info:tbNy-DRvQ8QJ:scholar.google.com/&output=cite&scirp=0&hl=en",
        "url_add_sclib": "/citations?hl=en&xsrf=&continue=/scholar%3Fq%3Drelated:LQgVvaxp8z0J:scholar.google.com/%26hl%3Den%26as_sdt%3D0,5&citilm=1&update_op=library_add&info=tbNy-DRvQ8QJ&ei=aYyAZtHKG7qWy9YP7pCPMA&json=",
        "num_citations": 62,
        "citedby_url": "/scholar?cites=14142269528170738613&as_sdt=2005&sciodt=0,5&hl=en",
        "url_related_articles": "/scholar?q=related:tbNy-DRvQ8QJ:scholar.google.com/&scioq=&hl=en&as_sdt=0,5"
    },
    "__1996_An_experimental_study": {
        "container_type": "Publication",
        "source": "PUBLICATION_SEARCH_SNIPPET",
        "bib": {
            "title": "An experimental study of SB-trees",
            "author": [
                "P Ferragina",
                "R Grossi"
            ],
            "pub_year": "1996",
            "venue": "Symposium on Discrete Algorithms",
            "abstract": "In a previous work of ours [13], we proposed a text indexing data structure for external memory, which we called SB-tree, that combines the best B-tree and suffix array qualities to"
        },
        "filled": false,
        "gsrank": 2,
        "pub_url": "https://www.researchgate.net/profile/Roberto-Grossi/publication/2486563_An_experimental_study_of_SB-trees/links/5433dcdc0cf2dc341dadc771/An-experimental-study-of-SB-trees.pdf",
        "author_id": [
            "3EILU3MAAAAJ",
            "yZTneswAAAAJ"
        ],
        "url_scholarbib": "/scholar?hl=en&q=info:7YJQgN5X-kkJ:scholar.google.com/&output=cite&scirp=1&hl=en",
        "url_add_sclib": "/citations?hl=en&xsrf=&continue=/scholar%3Fq%3Drelated:LQgVvaxp8z0J:scholar.google.com/%26hl%3Den%26as_sdt%3D0,5&citilm=1&update_op=library_add&info=7YJQgN5X-kkJ&ei=aYyAZtHKG7qWy9YP7pCPMA&json=",
        "num_citations": 14,
        "citedby_url": "/scholar?cites=5330669722093519597&as_sdt=2005&sciodt=0,5&hl=en",
        "url_related_articles": "/scholar?q=related:7YJQgN5X-kkJ:scholar.google.com/&scioq=&hl=en&as_sdt=0,5",
        "eprint_url": "https://www.researchgate.net/profile/Roberto-Grossi/publication/2486563_An_experimental_study_of_SB-trees/links/5433dcdc0cf2dc341dadc771/An-experimental-study-of-SB-trees.pdf"
    }
}