{
    "__2021_Human_migration_The": {
        "container_type": "Publication",
        "source": "PUBLICATION_SEARCH_SNIPPET",
        "bib": {
            "title": "Human migration: The big data perspective",
            "author": [
                "A S\u00eerbu",
                "G Andrienko",
                "N Andrienko",
                "C Boldrini"
            ],
            "pub_year": "2021",
            "venue": "International Journal of \u2026",
            "abstract": "How can big data help to understand the migration phenomenon? In this paper, we try to answer this question through an analysis of various phases of migration, comparing"
        },
        "filled": false,
        "gsrank": 1,
        "pub_url": "https://link.springer.com/article/10.1007/s41060-020-00213-5",
        "author_id": [
            "o-G11bQAAAAJ",
            "R370BREAAAAJ",
            "t8LK29QAAAAJ",
            "rCrzxbsAAAAJ"
        ],
        "url_scholarbib": "/scholar?hl=en&q=info:Frmk-wAUaDYJ:scholar.google.com/&output=cite&scirp=0&hl=en",
        "url_add_sclib": "/citations?hl=en&xsrf=&continue=/scholar%3Fq%3Drelated:lokbLJjlXbMJ:scholar.google.com/%26hl%3Den%26as_sdt%3D0,33&citilm=1&update_op=library_add&info=Frmk-wAUaDYJ&ei=YX-AZtqmDY6By9YP9NGdoA4&json=",
        "num_citations": 108,
        "citedby_url": "/scholar?cites=3920405470080448790&as_sdt=2005&sciodt=0,5&hl=en",
        "url_related_articles": "/scholar?q=related:Frmk-wAUaDYJ:scholar.google.com/&scioq=&hl=en&as_sdt=2005&sciodt=0,5",
        "eprint_url": "https://link.springer.com/content/pdf/10.1007/s41060-020-00213-5.pdf"
    },
    "__2020_Mining_high_quality": {
        "container_type": "Publication",
        "source": "PUBLICATION_SEARCH_SNIPPET",
        "bib": {
            "title": "Mining high quality patterns using multi-objective evolutionary algorithm",
            "author": [
                "W Fang",
                "Q Zhang",
                "J Sun",
                "X Wu"
            ],
            "pub_year": "2020",
            "venue": "IEEE Transactions on \u2026",
            "abstract": "Pattern mining (PM) refers to the process of discovering patterns of interest to users from data. However, most studies have considered only one pattern, such as frequent pattern or"
        },
        "filled": false,
        "gsrank": 2,
        "pub_url": "https://ieeexplore.ieee.org/abstract/document/9238432/",
        "author_id": [
            "TTcn20UAAAAJ",
            "hu2wWAwAAAAJ",
            "HEgT4CEAAAAJ",
            "x3p3o-YAAAAJ"
        ],
        "url_scholarbib": "/scholar?hl=en&q=info:e-PuCdXUe2YJ:scholar.google.com/&output=cite&scirp=1&hl=en",
        "url_add_sclib": "/citations?hl=en&xsrf=&continue=/scholar%3Fq%3Drelated:yuQ1uXSTPicJ:scholar.google.com/%26hl%3Den%26as_sdt%3D0,44&citilm=1&update_op=library_add&info=e-PuCdXUe2YJ&ei=SoWAZq6GKdS-6rQP5be_yAU&json=",
        "num_citations": 22,
        "citedby_url": "/scholar?cites=7384730025463833467&as_sdt=2005&sciodt=0,5&hl=en",
        "url_related_articles": "/scholar?q=related:e-PuCdXUe2YJ:scholar.google.com/&scioq=&hl=en&as_sdt=2005&sciodt=0,5"
    }
}